backend/__init__.py
backend/inference_core/__init__.py
backend/inference_core/algorithms/dbscan.py
backend/inference_core/algorithms/kmeans.py
backend/inference_core/algorithms/linear_regression.py
backend/inference_core/algorithms/range.py
backend/inference_core/algorithms/skyline_algorithm.py
backend/inference_core/core.py
backend/inference_core/filter.py
backend/inference_core/prediction.py
backend/inference_core/prediction_stats.py
backend/inference_core/rankings.py
backend/inference_core/reapply/__init__.py
backend/inference_core/reapply/compare.py
backend/inference_core/reapply/data_structures/add_plot_interaction.py
backend/inference_core/reapply/data_structures/apply_results.py
backend/inference_core/reapply/data_structures/base_interaction.py
backend/inference_core/reapply/data_structures/brush.py
backend/inference_core/reapply/data_structures/brush_interaction.py
backend/inference_core/reapply/data_structures/filter_interaction.py
backend/inference_core/reapply/data_structures/interactions.py
backend/inference_core/reapply/data_structures/plot.py
backend/inference_core/reapply/data_structures/point_selection_interaction.py
backend/inference_core/reapply/data_structures/select_prediction_interaction.py
backend/inference_core/reapply/data_structures/types.py
backend/inference_core/reapply/reapply.py
backend/inference_core/reapply/reapply_algorithms/algorithm_picker.py
backend/inference_core/reapply/reapply_algorithms/dbscan.py
backend/inference_core/reapply/reapply_algorithms/kmeans.py
backend/inference_core/reapply/reapply_algorithms/skyline.py
backend/inference_core/utils.py
backend/server/celery/init.py
backend/server/celery/tasks.py
backend/server/celery/utils.py
backend/server/database/get_predictions.py
backend/server/database/process_dataset.py
backend/server/database/schemas/__init__.py
backend/server/database/schemas/algorithms/cluster.py
backend/server/database/schemas/algorithms/intent_base.py
backend/server/database/schemas/algorithms/outlier.py
reusing_intent-0.1.2.dist-info/WHEEL
reusing_intent-0.1.2.dist-info/METADATA
reusing_intent-0.1.2.dist-info/RECORD
