Metadata-Version: 2.1
Name: reusing-intent
Version: 0.1.2
Summary: 
Author: Kiran Gadhave
Author-email: kirangadhave2@gmail.com
Requires-Python: >=3.8,<4.0
Classifier: Programming Language :: Python :: 3
Classifier: Programming Language :: Python :: 3.8
Classifier: Programming Language :: Python :: 3.9
Requires-Dist: Flask (>=1.1.2,<2.0.0)
Requires-Dist: Flask-Cors (>=3.0.9,<4.0.0)
Requires-Dist: PyYAML (>=5.3.1,<6.0.0)
Requires-Dist: SQLAlchemy (>=1.3.20,<2.0.0)
Requires-Dist: celery (>=5.0.5,<6.0.0)
Requires-Dist: numpy (>=1.19.4,<2.0.0)
Requires-Dist: pandas (>=1.1.4,<2.0.0)
Requires-Dist: paretoset (>=1.2.0,<2.0.0)
Requires-Dist: redis (>=3.5.3,<4.0.0)
Requires-Dist: requests (>=2.25.1,<3.0.0)
Requires-Dist: scikit-learn (>=0.23.2,<0.24.0)
Requires-Dist: tqdm (>=4.56.2,<5.0.0)
